{
  "kind": "collectionType",
  "collectionName": "galeris",
  "info": {
    "singularName": "galeri",
    "pluralName": "galeris",
    "displayName": "Galeri"
  },
  "options": {
    "draftAndPublish": true
  },
  "pluginOptions": {},
  "attributes": {
    "judul": {
      "type": "string",
      "required": true
    },
    "foto": {
      "allowedTypes": [
        "images"
      ],
      "type": "media",
      "multiple": false,
      "required": true
    },
    "deskripsi": {
      "type": "richtext"
    }
  }
}
